AnnoMate/AnnotationDisplayComponent.py
AnnoMate/Data.py
AnnoMate/MetadataHandler.py
AnnoMate/ReviewDataApp.py
AnnoMate/ReviewDataInterface.py
AnnoMate/ReviewerTemplate.py
AnnoMate/__init__.py
AnnoMate/AnnotationDisplayComponents/__init__.py
AnnoMate/AppComponents/CNVPlotComponent.py
AnnoMate/AppComponents/DataTableComponents.py
AnnoMate/AppComponents/MutationTableComponent.py
AnnoMate/AppComponents/PhylogicNDTComponents.py
AnnoMate/AppComponents/__init__.py
AnnoMate/AppComponents/utils.py
AnnoMate/DataTypes/GenericData.py
AnnoMate/DataTypes/PatientSampleData.py
AnnoMate/DataTypes/__init__.py
AnnoMate/Reviewers/ExampleReviewer.py
AnnoMate/Reviewers/__init__.py
AnnoMate-1.0.2.dist-info/LICENSE.txt
AnnoMate-1.0.2.dist-info/METADATA
AnnoMate-1.0.2.dist-info/WHEEL
AnnoMate-1.0.2.dist-info/top_level.txt
AnnoMate-1.0.2.dist-info/RECORD
