Metadata-Version: 2.1
Name: AnnoMate
Version: 1.0.2
Summary: A general tool to create dashboards for manual review
Home-page: https://github.com/getzlab/AnnoMate
Author: Claudia Chu
Author-email: cchu@broadinstitute.org
Project-URL: Bug Tracker, https://github.com/getzlab/AnnoMate/issues
Classifier: Programming Language :: Python :: 3
Classifier: License :: OSI Approved :: MIT License
Classifier: Operating System :: OS Independent
Requires-Python: >=3.8
License-File: LICENSE.txt
Requires-Dist: setuptools >=70.0.0
Requires-Dist: cnv-suite >=0.2.0
Requires-Dist: dash >=2.11.0
Requires-Dist: dash-bootstrap-components
Requires-Dist: dash-cytoscape
Requires-Dist: dash-daq
Requires-Dist: fsspec
Requires-Dist: gcsfs
Requires-Dist: google-auth
Requires-Dist: google-api-core
Requires-Dist: hound
Requires-Dist: ipykernel
Requires-Dist: ipython
Requires-Dist: jupyterlab >=4.0.2
Requires-Dist: matplotlib
Requires-Dist: pandas
Requires-Dist: pickleshare
Requires-Dist: pillow
Requires-Dist: pip
Requires-Dist: plotly >=5.15.0
Requires-Dist: scipy
Requires-Dist: frozendict
Requires-Dist: flask >=3.0.3
Requires-Dist: werkzeug >=2.3.3
